py_aseprite/__init__.py
py_aseprite/chunks.py
py_aseprite/headers.py
pygame_aseprite_animation/__init__.py
pygame_aseprite_animation/pygame_aseprite_animation.py
pygame_aseprite_animation-0.0.7.dist-info/LICENSE
pygame_aseprite_animation-0.0.7.dist-info/METADATA
pygame_aseprite_animation-0.0.7.dist-info/WHEEL
pygame_aseprite_animation-0.0.7.dist-info/top_level.txt
pygame_aseprite_animation-0.0.7.dist-info/RECORD
